<annotation>
	<folder>train</folder>
	<filename>51.jpg</filename>
	<path>F:\22.03.20\work\workspace\training_demo\images\train\51.jpg</path>
	<source>
		<database>Unknown</database>
	</source>
	<size>
		<width>750</width>
		<height>950</height>
		<depth>3</depth>
	</size>
	<segmented>0</segmented>
	<object>
		<name>Choi Woo-shik</name>
		<pose>Unspecified</pose>
		<truncated>0</truncated>
		<difficult>0</difficult>
		<bndbox>
			<xmin>353</xmin>
			<ymin>323</ymin>
			<xmax>439</xmax>
			<ymax>422</ymax>
		</bndbox>
	</object>
</annotation>
